{
	"format_version": "1.8.0",
	"animations": {
		"dance3": {
			"animation_length": 0.75,
			"bones": {
				"body": {
					"rotation": {
						"0.0": {
							"vector": [0, 720, 0]
						},
						"0.75": {
							"vector": [0, 0, 0]
						}
					}
				},
				"torso": {
					"rotation": {
						"0.0": {
							"vector": [0, 0, 0]
						},
						"0.1667": {
							"vector": [90, 0, -22.5]
						},
						"0.3333": {
							"vector": [90, 0, -125]
						},
						"0.5": {
							"vector": [90, 0, -125]
						},
						"0.75": {
							"vector": [0, 0, 0]
						}
					},
					"position": {
						"0.0": {
							"vector": [0, 0, 0]
						},
						"0.1667": {
							"vector": [3, -12, -2]
						},
						"0.3333": {
							"vector": [-2, -21, -2]
						},
						"0.5": {
							"vector": [-2, -21, -2]
						},
						"0.75": {
							"vector": [0, 0, 0]
						}
					}
				},
				"head": {
					"rotation": {
						"0.0": {
							"vector": [0, 0, 0]
						},
						"0.1667": {
							"vector": [0, 0, 0]
						},
						"0.3333": {
							"vector": [132.5, 0, -122.5]
						},
						"0.5": {
							"vector": [132.5, 0, -122.5]
						},
						"0.75": {
							"vector": [0, 0, 0]
						}
					},
					"position": {
						"0.0": {
							"vector": [0, 0, 0]
						},
						"0.1667": {
							"vector": [3, -15, -5]
						},
						"0.3333": {
							"vector": [-1, -21, -1]
						},
						"0.5": {
							"vector": [-1, -21, -1]
						},
						"0.75": {
							"vector": [0, 0, 0]
						}
					}
				},
				"right_arm": {
					"rotation": {
						"0.0": {
							"vector": [0, 0, 0]
						},
						"0.1667": {
							"vector": [0, 0, 0]
						},
						"0.3333": {
							"vector": [-5, 0, 187.5]
						},
						"0.5": {
							"vector": [-5, 0, 187.5]
						},
						"0.75": {
							"vector": [0, 0, 35]
						}
					},
					"position": {
						"0.0": {
							"vector": [0, 0, 0]
						},
						"0.1667": {
							"vector": [6, -12, 0]
						},
						"0.3333": {
							"vector": [1, -15, 0]
						},
						"0.5": {
							"vector": [1, -15, 0]
						},
						"0.625": {
							"vector": [2.5, -13.5, 0]
						},
						"0.75": {
							"vector": [0, 0, 0]
						}
					}
				},
				"left_arm": {
					"rotation": {
						"0.0": {
							"vector": [0, 0, 0]
						},
						"0.1667": {
							"vector": [0, 0, -125]
						},
						"0.3333": {
							"vector": [-28.88636, -15.58394, -100.96295]
						},
						"0.5": {
							"vector": [-28.88636, -15.58394, -100.96295]
						},
						"0.75": {
							"vector": [-25.68482, 10.17781, -4.82607]
						}
					},
					"position": {
						"0.0": {
							"vector": [0, 0, 0]
						},
						"0.1667": {
							"vector": [3, -10, 0]
						},
						"0.3333": {
							"vector": [-3, -24, 0]
						},
						"0.5": {
							"vector": [-3, -24, 0]
						},
						"0.625": {
							"vector": [-1.5, -8, 0]
						},
						"0.75": {
							"vector": [0, 0, 0]
						}
					}
				},
				"right_leg": {
					"rotation": {
						"0.0": {
							"vector": [0, 0, 0]
						},
						"0.1667": {
							"vector": [90, -20, 0]
						},
						"0.3333": {
							"vector": [55.64932, -12.23793, -111.44533]
						},
						"0.5": {
							"vector": [55.64932, -12.23793, -111.44533]
						},
						"0.75": {
							"vector": [17.5, 0, 0]
						}
					},
					"position": {
						"0.0": {
							"vector": [0, 0, 0]
						},
						"0.1667": {
							"vector": [3, -1, 10]
						},
						"0.3333": {
							"vector": [1, -11, 10]
						},
						"0.5": {
							"vector": [1, -11, 10]
						},
						"0.625": {
							"vector": [7.5, -3.5, 7]
						},
						"0.75": {
							"vector": [0, 0, 0]
						}
					}
				},
				"left_leg": {
					"rotation": {
						"0.0": {
							"vector": [0, 0, 0]
						},
						"0.1667": {
							"vector": [90, 20, 0]
						},
						"0.3333": {
							"vector": [67.10005, 27.2178, -126.04555]
						},
						"0.5": {
							"vector": [67.10005, 27.2178, -126.04555]
						},
						"0.75": {
							"vector": [-12.5, 0, 0]
						}
					},
					"position": {
						"0.0": {
							"vector": [0, 0, 0]
						},
						"0.1667": {
							"vector": [3, 1, 10]
						},
						"0.3333": {
							"vector": [-5, -7, 10]
						},
						"0.5": {
							"vector": [-5, -7, 10]
						},
						"0.625": {
							"vector": [5.5, -0.5, 7]
						},
						"0.75": {
							"vector": [0, 0, 0]
						}
					}
				}
			}
		}
	},
	"geckolib_format_version": 2
}