{
  "display": {
    "icon": {
      "item": "minecraft:orange_dye"
    },
    "title": {
      "translate": "advancements.battle_yuji_itadori_shinjuku.title"
    },
    "description": {
      "translate": "advancements.battle_yuji_itadori_shinjuku.descr"
    },
    "frame": "challenge",
    "show_toast": true,
    "announce_to_chat": true,
    "hidden": false
  },
  "criteria": {
    "battle_yuji_itadori_shinjuku_0": {
      "trigger": "minecraft:impossible"
    }
  },
  "parent": "gaigegaigekaigecraft:battle_yuji_itadori_shibuya"
}